LICENSE
MANIFEST.in
Makefile
README.rst
setup.py
bandicoot/__init__.py
bandicoot/core.py
bandicoot/individual.py
bandicoot/io.py
bandicoot/network.py
bandicoot/recharge.py
bandicoot/spatial.py
bandicoot/utils.py
bandicoot/visualization.py
bandicoot/weekmatrix.py
bandicoot.egg-info/PKG-INFO
bandicoot.egg-info/SOURCES.txt
bandicoot.egg-info/dependency_links.txt
bandicoot.egg-info/requires.txt
bandicoot.egg-info/top_level.txt
bandicoot/dashboard_src/package.json
bandicoot/dashboard_src/public/index.html
bandicoot/dashboard_src/public/build/app.js
bandicoot/dashboard_src/public/build/main.css
bandicoot/dashboard_src/public/data/bc_export.json
bandicoot/dashboard_src/public/fonts/opensans-400.woff
bandicoot/dashboard_src/public/js/app.js
bandicoot/dashboard_src/public/js/indicator_chart.js
bandicoot/dashboard_src/public/js/network.js
bandicoot/dashboard_src/public/js/timescale_brush.js
bandicoot/dashboard_src/public/js/utils.js
bandicoot/dashboard_src/public/sass/main.scss
bandicoot/helper/__init__.py
bandicoot/helper/group.py
bandicoot/helper/maths.py
bandicoot/helper/stops.py
bandicoot/helper/tools.py
bandicoot/tests/__init__.py
bandicoot/tests/generate_user.py
bandicoot/tests/test_core.py
bandicoot/tests/test_export.py
bandicoot/tests/test_group.py
bandicoot/tests/test_manual.py
bandicoot/tests/test_network.py
bandicoot/tests/test_parsers.py
bandicoot/tests/test_regressions.py
bandicoot/tests/test_sequences.py
bandicoot/tests/test_spatial.py
bandicoot/tests/test_special.py
bandicoot/tests/test_utils.py
bandicoot/tests/testing_tools.py