Metadata-Version: 2.1
Name: bandicoot
Version: 0.6.0
Summary: A toolbox to analyze mobile phone metadata.
Home-page: https://github.com/computationalprivacy/bandicoot
Author: Yves-Alexandre de Montjoye
Author-email: yvesalexandre@demontjoye.com
License: MIT
Platform: UNKNOWN
Classifier: Environment :: Plugins
Classifier: Intended Audience :: Science/Research
Classifier: License :: OSI Approved :: MIT License
Classifier: Programming Language :: Python
Classifier: Programming Language :: Python :: 2
Classifier: Programming Language :: Python :: 2.7
Classifier: Programming Language :: Python :: 3
Classifier: Topic :: Scientific/Engineering :: Information Analysis
Classifier: Topic :: Scientific/Engineering :: Mathematics
Provides-Extra: tests
